things_mcp/__init__.py
things_mcp/config.py
things_mcp/fast_server.py
things_mcp/formatters.py
things_mcp/handlers.py
things_mcp/mcp_tools.py
things_mcp/things_server.py
things_mcp/url_scheme.py
things_mcp/utils.py
things_fastmcp-1.0.0.dist-info/METADATA
things_fastmcp-1.0.0.dist-info/WHEEL
things_fastmcp-1.0.0.dist-info/entry_points.txt
things_fastmcp-1.0.0.dist-info/licenses/LICENSE
things_fastmcp-1.0.0.dist-info/RECORD
