Metadata-Version: 2.4
Name: things-fastmcp
Version: 1.0.0
Summary: Things app Model Context Protocol (MCP) server for Claude and Anthropic Windsurf
Project-URL: Homepage, https://github.com/excelsier/things-mcp
Project-URL: Bug Tracker, https://github.com/excelsier/things-mcp/issues
Project-URL: Documentation, https://github.com/excelsier/things-mcp#readme
Author-email: Harald Lindstrøm <hald@users.noreply.github.com>, excelsier <51231325+excelsier@users.noreply.github.com>
License: MIT License
License-File: LICENSE
Keywords: anthropic,claude,mcp,productivity,task-management,things
Classifier: Development Status :: 4 - Beta
Classifier: Intended Audience :: End Users/Desktop
Classifier: License :: OSI Approved :: MIT License
Classifier: Programming Language :: Python :: 3.12
Classifier: Topic :: Office/Business :: Scheduling
Classifier: Topic :: Software Development :: Libraries :: Python Modules
Classifier: Topic :: Utilities
Requires-Python: >=3.12
Requires-Dist: httpx>=0.28.1
Requires-Dist: mcp[cli]>=1.2.0
Requires-Dist: things-py>=0.0.15
Provides-Extra: dev
Requires-Dist: build>=0.10.0; extra == 'dev'
Requires-Dist: pytest-cov>=4.0.0; extra == 'dev'
Requires-Dist: pytest>=7.0.0; extra == 'dev'
Requires-Dist: ruff>=0.1.0; extra == 'dev'
Requires-Dist: twine>=4.0.0; extra == 'dev'
